setup.py
distributions_ldorogi/Binomialdistribution.py
distributions_ldorogi/Gaussiandistribution.py
distributions_ldorogi/Generaldistribution.py
distributions_ldorogi/__init__.py
distributions_ldorogi.egg-info/PKG-INFO
distributions_ldorogi.egg-info/SOURCES.txt
distributions_ldorogi.egg-info/dependency_links.txt
distributions_ldorogi.egg-info/not-zip-safe
distributions_ldorogi.egg-info/top_level.txt